chkexmpt/__init__.py
chkexmpt/main.py
chkexmpt-0.2.0.dist-info/LICENSE
chkexmpt-0.2.0.dist-info/METADATA
chkexmpt-0.2.0.dist-info/WHEEL
chkexmpt-0.2.0.dist-info/entry_points.txt
chkexmpt-0.2.0.dist-info/top_level.txt
chkexmpt-0.2.0.dist-info/RECORD
