Metadata-Version: 2.1
Name: chkexmpt
Version: 0.2.0
Summary: Check for unintentional security exemptions.
Home-page: https://github.com/2ffs2nns/check-exemptions
Author: Eric Hoffmann
Author-email: 2ffs2nns@gmail.com
Requires-Python: >=3.8
License-File: LICENSE
